cf_ips_to_hcloud_fw/__init__.py
cf_ips_to_hcloud_fw/__main__.py
cf_ips_to_hcloud_fw/cloudflare.py
cf_ips_to_hcloud_fw/config.py
cf_ips_to_hcloud_fw/custom_logging.py
cf_ips_to_hcloud_fw/firewall.py
cf_ips_to_hcloud_fw/models.py
cf_ips_to_hcloud_fw/py.typed
cf_ips_to_hcloud_fw-1.2.0.dist-info/licenses/LICENSE
cf_ips_to_hcloud_fw-1.2.0.dist-info/WHEEL
cf_ips_to_hcloud_fw-1.2.0.dist-info/entry_points.txt
cf_ips_to_hcloud_fw-1.2.0.dist-info/METADATA
cf_ips_to_hcloud_fw-1.2.0.dist-info/RECORD
