Metadata-Version: 2.4
Name: cf-ips-to-hcloud-fw
Version: 1.2.0
Summary: Update Hetzner Cloud firewall rules with Cloudflare IP ranges
Keywords: cloudflare,hcloud,hetzner,firewall,cli
Author: Jürgen Kreileder
Author-email: jk@blackdown.de
License-Expression: MIT
License-File: LICENSE
Classifier: Development Status :: 5 - Production/Stable
Classifier: Environment :: Console
Classifier: Environment :: Other Environment
Classifier: Intended Audience :: Developers
Classifier: Intended Audience :: System Administrators
Classifier: Natural Language :: English
Classifier: Operating System :: OS Independent
Classifier: Programming Language :: Python :: 3
Classifier: Programming Language :: Python :: 3.10
Classifier: Programming Language :: Python :: 3.11
Classifier: Programming Language :: Python :: 3.12
Classifier: Programming Language :: Python :: 3.13
Classifier: Programming Language :: Python :: 3.14
Classifier: Programming Language :: Python :: Implementation :: CPython
Classifier: Topic :: Internet
Classifier: Topic :: System :: Networking :: Firewalls
Classifier: Topic :: Utilities
Requires-Dist: cloudflare>=4.3.1
Requires-Dist: hcloud>=2.11.1
Requires-Dist: pydantic>=2.12.4
Requires-Dist: pyyaml>=6.0.3
Requires-Python: >=3.10
Project-URL: Bluesky, https://bsky.app/profile/jk.blackdown.de
Project-URL: Changelog, https://github.com/jkreileder/cf-ips-to-hcloud-fw/blob/main/CHANGELOG.md
Project-URL: Documentation, https://github.com/jkreileder/cf-ips-to-hcloud-fw
Project-URL: Homepage, https://github.com/jkreileder/cf-ips-to-hcloud-fw
Project-URL: Issues, https://github.com/jkreileder/cf-ips-to-hcloud-fw/issues
Project-URL: PyPI, https://pypi.org/project/cf-ips-to-hcloud-fw/
Project-URL: Source, https://github.com/jkreileder/cf-ips-to-hcloud-fw
Project-URL: X, https://x.com/jkreileder
